LICENSE
README.md
setup.py
bin/blipctl
pythonblip/__init__.py
pythonblip/client.py
pythonblip/exceptions.py
pythonblip/frame.py
pythonblip/headers.py
pythonblip/output.py
pythonblip/protocol.py
pythonblip/replicator.py
pythonblip/varint.py
pythonblip.egg-info/PKG-INFO
pythonblip.egg-info/SOURCES.txt
pythonblip.egg-info/dependency_links.txt
pythonblip.egg-info/requires.txt
pythonblip.egg-info/top_level.txt