Metadata-Version: 2.1
Name: pythonblip
Version: 0.2.1
Summary: Couchbase BLIP Protocol Library
Home-page: https://github.com/mminichino/python-blip
Author: Michael Minichino
Author-email: info@unix.us.com
License: Apache License 2.0
Keywords: couchbase,blip,mobile,syncgateway
Classifier: Development Status :: 4 - Beta
Classifier: License :: OSI Approved :: Apache Software License
Classifier: Intended Audience :: Developers
Classifier: Operating System :: OS Independent
Classifier: Programming Language :: Python
Classifier: Programming Language :: Python :: 3
Classifier: Topic :: Database
Classifier: Topic :: System :: Networking
Classifier: Topic :: Software Development :: Libraries
Classifier: Topic :: Software Development :: Libraries :: Python Modules
Requires-Python: >=3.9
License-File: LICENSE
